wikitojson.py
wikitojson-0.0.3.dist-info/LICENSE
wikitojson-0.0.3.dist-info/METADATA
wikitojson-0.0.3.dist-info/WHEEL
wikitojson-0.0.3.dist-info/top_level.txt
wikitojson-0.0.3.dist-info/RECORD
