Metadata-Version: 2.1
Name: wikitojson
Version: 0.0.3
Summary: Wikipedia(English) to json
Home-page: https://github.com/Klaifer/wikitojson
Author: Klaifer Garcia
License: UNKNOWN
Platform: UNKNOWN
Classifier: Programming Language :: Python :: 3
Classifier: License :: OSI Approved :: MIT License
Classifier: Operating System :: OS Independent
Requires-Python: >=3.6
